<?xml version = '1.0' encoding = 'UTF-8'?>
<Relation class="oracle.dbtools.crest.model.design.logical.Relation" name="reg-car" directorySegmentName="seg_0" id="56A89F12-A6F8-8A92-BA16-957BF5EF7FCC">
<createdBy>Pomochka</createdBy>
<createdTime>2024-04-12 09:42:29 UTC</createdTime>
<ownerDesignName>ER_L.Roman</ownerDesignName>
<engineerTo>
<item key="824CFA09-1A46-3178-986F-E6397D0D78EE" value="true"/>
</engineerTo>
<identifying>false</identifying>
<nameOnSource>Имеет</nameOnSource>
<nameOnTarget>Находится</nameOnTarget>
<optionalSource>false</optionalSource>
<optionalTarget>true</optionalTarget>
<sourceCardinality>1</sourceCardinality>
<sourceEntity>B000FECE-5C0B-4678-1328-67D848915A2B</sourceEntity>
<targetCardinalityString>*</targetCardinalityString>
<targetEntity>06785200-36BE-55B4-37CD-2CC1A694C542</targetEntity>
<transferable>true</transferable>
<deleteRule>NO ACTION</deleteRule>
</Relation>